{
  "_id": "lj9vB9hzl7Nd1caB",
  "name": "Ipt (Roanwood)",
  "type": "consumable",
  "flags": {
    "betterRolls5e": {
      "critRange": {
        "value": null
      },
      "critDamage": {
        "value": ""
      },
      "quickDesc": {
        "value": true,
        "altValue": true
      },
      "quickProperties": {
        "value": true,
        "altValue": true
      },
      "quickOther": {
        "value": true,
        "altValue": true
      },
      "quickFlavor": {
        "value": true,
        "altValue": true
      },
      "quickCharges": {
        "value": {
          "quantity": false
        },
        "altValue": {
          "quantity": false
        }
      }
    }
  },
  "img": "modules/brodericks-compendium/icons/tree.svg",
  "effects": [],
  "system": {
    "description": {
      "value": "<p><em>Biome: Jungles</em></p>\n<p>Trees, commonly used in wand and magestaff construction, that grow upwards of 100 feet tall. Although the trees can grow incredibly large, their branches are relatively close to the ground, hanging a mere 30 feet from the forest floor. Their leaves are fan-shaped and about a foot in length, while their bark is reddish-brown speckled with gray. The wood is not as hard or as strong as coldwood, bronzewood, or oak, but it is suitable for delicate furnishings.</p>",
      "chat": "",
      "unidentified": ""
    },
    "source": "Broderick's Compendium: Plants and Fungi Across the Realm (version 2.0)",
    "quantity": 1,
    "weight": {
      "value": 0,
      "units": "lb"
    },
    "price": 0,
    "attunement": 0,
    "equipped": false,
    "rarity": "common",
    "identified": true,
    "activation": {
      "type": "",
      "cost": null,
      "condition": ""
    },
    "duration": {
      "value": null,
      "units": ""
    },
    "cover": null,
    "crewed": false,
    "target": {
      "value": null,
      "width": null,
      "units": "",
      "type": ""
    },
    "range": {
      "value": null,
      "long": null,
      "units": ""
    },
    "uses": {
      "value": null,
      "max": 0,
      "per": null,
      "recovery": "",
      "autoDestroy": false
    },
    "consume": {
      "type": "",
      "target": null,
      "amount": null
    },
    "ability": null,
    "actionType": "",
    "attackBonus": 0,
    "chatFlavor": "",
    "critical": null,
    "damage": {
      "parts": [],
      "versatile": ""
    },
    "formula": "",
    "save": {
      "ability": "",
      "dc": null,
      "scaling": "spell"
    },
    "consumableType": "potion",
    "attuned": false
  },
  "ownership": {
    "default": 0
  },
  "folder": null,
  "sort": 0,
  "_stats": {
    "systemId": "dnd5e",
    "systemVersion": "2.2.1",
    "coreVersion": "12.328",
    "createdTime": null,
    "modifiedTime": 1698241158871,
    "lastModifiedBy": "packsbuilder0000",
    "compendiumSource": null,
    "duplicateSource": null
  },
  "_key": "!items!lj9vB9hzl7Nd1caB"
}
